timepro/__init__.py
timepro/deadline_tracker/__init__.py
timepro/deadline_tracker/deadline_tracker.py
timepro/goal_settings/__init__.py
timepro/goal_settings/goal_settings.py
timepro/habit_tracker/__init__.py
timepro/habit_tracker/habit_tracker.py
timepro/pomodoro_timer/__init__.py
timepro/pomodoro_timer/pomodoro_timer.py
timepro/task_management/__init__.py
timepro/task_management/task_management.py
timepro/time_analysis/__init__.py
timepro/time_analysis/time_analysis.py
timepro-0.0.4.dist-info/LICENSE.txt
timepro-0.0.4.dist-info/METADATA
timepro-0.0.4.dist-info/WHEEL
timepro-0.0.4.dist-info/top_level.txt
timepro-0.0.4.dist-info/RECORD
