Metadata-Version: 2.1
Name: timepro
Version: 0.0.4
Summary: A package for managing time effectively, including Pomodoro Timer, Task Manager, Deadline Tracker, and more.
Home-page: https://github.com/Faderu/TimePRO
Author: KELOMPOK 7 ALGORITMA A
Author-email: fadhilbosque@gmail.com
License: MIT
Keywords: pomodoro timer task manager deadline tracker
Classifier: Development Status :: 5 - Production/Stable
Classifier: Intended Audience :: Education
Classifier: Operating System :: Microsoft :: Windows :: Windows 10
Classifier: License :: OSI Approved :: MIT License
Classifier: Programming Language :: Python :: 3
License-File: LICENSE.txt
